simpleml/__init__.py
simpleml/constants.py
simpleml/imports.py
simpleml/_external/__init__.py
simpleml/_external/joblib.py
simpleml/adapters/__init__.py
simpleml/cli/__init__.py
simpleml/cli/database.py
simpleml/cli/main.py
simpleml/datasets/__init__.py
simpleml/datasets/base_dataset.py
simpleml/datasets/dataset_splits.py
simpleml/datasets/dask/__init__.py
simpleml/datasets/dask/base.py
simpleml/datasets/dask/file_based.py
simpleml/datasets/dask/pipeline.py
simpleml/datasets/numpy/__init__.py
simpleml/datasets/numpy/base.py
simpleml/datasets/numpy/pipeline.py
simpleml/datasets/pandas/__init__.py
simpleml/datasets/pandas/base.py
simpleml/datasets/pandas/file_based.py
simpleml/datasets/pandas/pipeline.py
simpleml/datasets/ray/__init__.py
simpleml/datasets/tensorflow/__init__.py
simpleml/executors/__init__.py
simpleml/executors/airflow/__init__.py
simpleml/executors/beam/__init__.py
simpleml/executors/dask/__init__.py
simpleml/executors/kubernetes/__init__.py
simpleml/executors/multiprocessing/__init__.py
simpleml/executors/ray/__init__.py
simpleml/executors/threading/__init__.py
simpleml/metrics/__init__.py
simpleml/metrics/base_metric.py
simpleml/metrics/classification.py
simpleml/migrations/__init__.py
simpleml/migrations/alembic.ini
simpleml/migrations/env.py
simpleml/migrations/script.py.mako
simpleml/migrations/versions/0680f18b52ca_empty_database.py
simpleml/migrations/versions/5c2f66bdf2ae_pandas_datasets_squeezing.py
simpleml/migrations/versions/7c48d821e9fa_dataset_split_sections.py
simpleml/migrations/versions/9df691c76c63_base_schema.py
simpleml/migrations/versions/__init__.py
simpleml/migrations/versions/deefa69553d8_hash_datatype.py
simpleml/migrations/versions/gjevp90284z9_multiple_filepaths.py
simpleml/migrations/versions/k65erd8bf5d0_metric_datasets.py
simpleml/models/__init__.py
simpleml/models/base_keras_model.py
simpleml/models/base_model.py
simpleml/models/base_sklearn_model.py
simpleml/models/external_models.py
simpleml/models/split_iterators.py
simpleml-0.14.0.dist-info/LICENSE
simpleml-0.14.0.dist-info/METADATA
simpleml-0.14.0.dist-info/WHEEL
simpleml-0.14.0.dist-info/entry_points.txt
simpleml-0.14.0.dist-info/top_level.txt
simpleml-0.14.0.dist-info/RECORD
